harfile/__init__.py
harfile/_models.py
harfile/_version.py
harfile-0.3.1.dist-info/METADATA
harfile-0.3.1.dist-info/WHEEL
harfile-0.3.1.dist-info/licenses/LICENSE
harfile-0.3.1.dist-info/RECORD
